py-essl-contact/__init__.py
py-essl-contact/schema.py
py-essl-contact/service.py
tests/__init__.py
tests/test_copyright.py
tests/test_service.py
py_essl_contact-0.1.dist-info/LICENSE
py_essl_contact-0.1.dist-info/METADATA
py_essl_contact-0.1.dist-info/WHEEL
py_essl_contact-0.1.dist-info/top_level.txt
py_essl_contact-0.1.dist-info/RECORD
