Metadata-Version: 2.1
Name: py-essl-contact
Version: 0.1
Summary: ESSL users management
Home-page: UNKNOWN
Author: Femi Adigun
Author-email: femi.adigun@myeverlasting.net
License: UNKNOWN
Keywords: fastapi,ESSL,ReachAI
Platform: UNKNOWN
License-File: LICENSE
Requires-Dist: bcrypt ==4.1.2
Requires-Dist: pytest ==8.1.1
Requires-Dist: pydantic ==2.7.1
Requires-Dist: sqlalchemy ==2.0.29
